pixtrail/__init__.py
pixtrail/__main__.py
pixtrail/cli.py
pixtrail/core.py
pixtrail/exif_reader.py
pixtrail/gpx_generator.py
pixtrail/utils.py
pixtrail/web/__init__.py
pixtrail/web/routes.py
pixtrail/web/server.py
pixtrail/web/static/css/main.css
pixtrail/web/static/js/main.js
pixtrail/web/templates/index.html
pixtrail-2.3.3.dist-info/licenses/LICENSE
tests/__init__.py
tests/test_core.py
tests/test_exif_reader.py
tests/test_gpx_generator.py
tests/test_utils.py
pixtrail-2.3.3.dist-info/METADATA
pixtrail-2.3.3.dist-info/WHEEL
pixtrail-2.3.3.dist-info/entry_points.txt
pixtrail-2.3.3.dist-info/top_level.txt
pixtrail-2.3.3.dist-info/RECORD
