Metadata-Version: 2.4
Name: pixtrail
Version: 2.3.3
Summary: Extract GPS data from photos and create GPX files
Home-page: https://github.com/sukitsubaki/pixtrail
Author: Suki Tsubaki
License: MIT
Project-URL: Homepage, https://github.com/sukitsubaki/pixtrail
Project-URL: Issues, https://github.com/sukitsubaki/pixtrail/issues
Classifier: Programming Language :: Python :: 3
Classifier: Operating System :: OS Independent
Requires-Python: >=3.6
License-File: LICENSE
Requires-Dist: exifread>=3.0.0
Requires-Dist: gpxpy>=1.5.0
Requires-Dist: pillow>=9.0.0
Provides-Extra: web
Requires-Dist: flask>=2.0.0; extra == "web"
Requires-Dist: werkzeug>=2.0.0; extra == "web"
Provides-Extra: dev
Requires-Dist: pytest>=6.0.0; extra == "dev"
Requires-Dist: black>=21.5b2; extra == "dev"
Requires-Dist: mypy>=0.812; extra == "dev"
Requires-Dist: isort>=5.9.1; extra == "dev"
Requires-Dist: mkdocs>=1.4.0; extra == "dev"
Requires-Dist: mkdocs-material>=8.0.0; extra == "dev"
Dynamic: home-page
Dynamic: license-file
Dynamic: requires-python
